{"data":{"weekly_report":{"date":"27 Feb 19 To 06 Mar 19","innerData":{"vsadesktopWindows_2012_R2chromebetaWeeklyHealth":{"data":[{"fail":"0 (0.0%)","total":1,"pass":"1 (100.0%)","module":"rerun","name":"Pass","link":"http://qa-auto01.on24.com:8080/jenkins/job/qa-vsa-desktop-sl/SELENIUM_DRIVER=Windows_2012_R2chromebeta,TEST_SET=rerun/5588/cucumber-html-reports","hex":"#8BC34A","time":"0h 2min","value":100,"config":"Win 8.1 chrome (b)"},{"fail":"0 (0.0%)","total":1,"pass":"1 (100.0%)","module":"rerun","name":"Fail","link":"http://qa-auto01.on24.com:8080/jenkins/job/qa-vsa-desktop-sl/SELENIUM_DRIVER=Windows_2012_R2chromebeta,TEST_SET=rerun/5588/cucumber-html-reports","hex":"#b22200","time":"0h 2min","value":0,"config":"Win 8.1 chrome (b)"},{"fail":"0 (0.0%)","total":16,"pass":"16 (100.0%)","module":"green","name":"Pass","link":"http://qa-auto01.on24.com:8080/jenkins/job/qa-vsa-desktop-sl/SELENIUM_DRIVER=Windows_2012_R2chromebeta,TEST_SET=green/5629/cucumber-html-reports","hex":"#8BC34A","time":"0h 9min","value":100,"config":"Win 8.1 chrome (b)"},{"fail":"0 (0.0%)","total":16,"pass":"16 (100.0%)","module":"green","name":"Fail","link":"http://qa-auto01.on24.com:8080/jenkins/job/qa-vsa-desktop-sl/SELENIUM_DRIVER=Windows_2012_R2chromebeta,TEST_SET=green/5629/cucumber-html-reports","hex":"#b22200","time":"0h 9min","value":0,"config":"Win 8.1 chrome (b)"},{"fail":"1 (0.7%)","total":137,"pass":"136 (99.3%)","module":"daily1","name":"Pass","link":"http://qa-auto01.on24.com:8080/jenkins/job/qa-vsa-desktop-sl/SELENIUM_DRIVER=Windows_2012_R2chromebeta,TEST_SET=daily1/5630/cucumber-html-reports","hex":"#8BC34A","time":"1h 49min","value":99.3,"config":"Win 8.1 chrome (b)"},{"fail":"1 (0.7%)","total":137,"pass":"136 (99.3%)","module":"daily1","name":"Fail","link":"http://qa-auto01.on24.com:8080/jenkins/job/qa-vsa-desktop-sl/SELENIUM_DRIVER=Windows_2012_R2chromebeta,TEST_SET=daily1/5630/cucumber-html-reports","hex":"#b22200","time":"1h 49min","value":0.7,"config":"Win 8.1 chrome (b)"},{"fail":"0 (0.0%)","total":170,"pass":"170 (100.0%)","module":"daily2","name":"Pass","link":"http://qa-auto01.on24.com:8080/jenkins/job/qa-vsa-desktop-sl/SELENIUM_DRIVER=Windows_2012_R2chromebeta,TEST_SET=daily2/5587/cucumber-html-reports","hex":"#8BC34A","time":"1h 18min","value":100,"config":"Win 8.1 chrome (b)"},{"fail":"0 (0.0%)","total":170,"pass":"170 (100.0%)","module":"daily2","name":"Fail","link":"http://qa-auto01.on24.com:8080/jenkins/job/qa-vsa-desktop-sl/SELENIUM_DRIVER=Windows_2012_R2chromebeta,TEST_SET=daily2/5587/cucumber-html-reports","hex":"#b22200","time":"1h 18min","value":0,"config":"Win 8.1 chrome (b)"}],"title":"Weekly Health - VE Desktop (Win 8.1 chrome (b))"},"vsadesktopWindows_10microsoftedge14WeeklyHealth":{"data":[{"fail":"5 (83.3%)","total":6,"pass":"1 (16.7%)","module":"rerun","name":"Pass","link":"http://qa-auto01.on24.com:8080/jenkins/job/qa-vsa-desktop-sl/SELENIUM_DRIVER=Windows_10microsoftedge14,TEST_SET=rerun/0/cucumber-html-reports","hex":"#8BC34A","time":"0h 9min","value":16.7,"config":"Win 10 ms edge 14"},{"fail":"5 (83.3%)","total":6,"pass":"1 (16.7%)","module":"rerun","name":"Fail","link":"http://qa-auto01.on24.com:8080/jenkins/job/qa-vsa-desktop-sl/SELENIUM_DRIVER=Windows_10microsoftedge14,TEST_SET=rerun/0/cucumber-html-reports","hex":"#b22200","time":"0h 9min","value":83.3,"config":"Win 10 ms edge 14"},{"fail":"0 (0.0%)","total":17,"pass":"17 (100.0%)","module":"green","name":"Pass","link":"http://qa-auto01.on24.com:8080/jenkins/job/qa-vsa-desktop-sl/SELENIUM_DRIVER=Windows_10microsoftedge14,TEST_SET=green/0/cucumber-html-reports","hex":"#8BC34A","time":"0h 5min","value":100,"config":"Win 10 ms edge 14"},{"fail":"0 (0.0%)","total":17,"pass":"17 (100.0%)","module":"green","name":"Fail","link":"http://qa-auto01.on24.com:8080/jenkins/job/qa-vsa-desktop-sl/SELENIUM_DRIVER=Windows_10microsoftedge14,TEST_SET=green/0/cucumber-html-reports","hex":"#b22200","time":"0h 5min","value":0,"config":"Win 10 ms edge 14"},{"fail":"2 (1.1%)","total":175,"pass":"173 (98.9%)","module":"daily1","name":"Pass","link":"http://qa-auto01.on24.com:8080/jenkins/job/qa-vsa-desktop-sl/SELENIUM_DRIVER=Windows_10microsoftedge14,TEST_SET=daily1/0/cucumber-html-reports","hex":"#8BC34A","time":"1h 8min","value":98.9,"config":"Win 10 ms edge 14"},{"fail":"2 (1.1%)","total":175,"pass":"173 (98.9%)","module":"daily1","name":"Fail","link":"http://qa-auto01.on24.com:8080/jenkins/job/qa-vsa-desktop-sl/SELENIUM_DRIVER=Windows_10microsoftedge14,TEST_SET=daily1/0/cucumber-html-reports","hex":"#b22200","time":"1h 8min","value":1.1,"config":"Win 10 ms edge 14"},{"fail":"4 (2.3%)","total":173,"pass":"169 (97.7%)","module":"daily2","name":"Pass","link":"http://qa-auto01.on24.com:8080/jenkins/job/qa-vsa-desktop-sl/SELENIUM_DRIVER=Windows_10microsoftedge14,TEST_SET=daily2/0/cucumber-html-reports","hex":"#8BC34A","time":"1h 3min","value":97.7,"config":"Win 10 ms edge 14"},{"fail":"4 (2.3%)","total":173,"pass":"169 (97.7%)","module":"daily2","name":"Fail","link":"http://qa-auto01.on24.com:8080/jenkins/job/qa-vsa-desktop-sl/SELENIUM_DRIVER=Windows_10microsoftedge14,TEST_SET=daily2/0/cucumber-html-reports","hex":"#b22200","time":"1h 3min","value":2.3,"config":"Win 10 ms edge 14"}],"title":"Weekly Health - VE Desktop (Win 10 ms edge 14)"},"vsadesktopWindows_2012_R2internet_explorer11WeeklyHealth":{"data":[{"fail":"2 (100.0%)","total":2,"pass":"0 (0.0%)","module":"rerun","name":"Pass","link":"http://qa-auto01.on24.com:8080/jenkins/job/qa-vsa-desktop-sl/SELENIUM_DRIVER=Windows_2012_R2internet_explorer11,TEST_SET=rerun/5613/cucumber-html-reports","hex":"#8BC34A","time":"0h 4min","value":0,"config":"Win 8.1 IE 11"},{"fail":"2 (100.0%)","total":2,"pass":"0 (0.0%)","module":"rerun","name":"Fail","link":"http://qa-auto01.on24.com:8080/jenkins/job/qa-vsa-desktop-sl/SELENIUM_DRIVER=Windows_2012_R2internet_explorer11,TEST_SET=rerun/5613/cucumber-html-reports","hex":"#b22200","time":"0h 4min","value":100,"config":"Win 8.1 IE 11"},{"fail":"17 (100.0%)","total":17,"pass":"0 (0.0%)","module":"green","name":"Pass","link":"http://qa-auto01.on24.com:8080/jenkins/job/qa-vsa-desktop-sl/SELENIUM_DRIVER=Windows_2012_R2internet_explorer11,TEST_SET=green/0/cucumber-html-reports","hex":"#8BC34A","time":"0h 45min","value":0,"config":"Win 8.1 IE 11"},{"fail":"17 (100.0%)","total":17,"pass":"0 (0.0%)","module":"green","name":"Fail","link":"http://qa-auto01.on24.com:8080/jenkins/job/qa-vsa-desktop-sl/SELENIUM_DRIVER=Windows_2012_R2internet_explorer11,TEST_SET=green/0/cucumber-html-reports","hex":"#b22200","time":"0h 45min","value":100,"config":"Win 8.1 IE 11"},{"fail":"0 (0.0%)","total":137,"pass":"137 (100.0%)","module":"daily1","name":"Pass","link":"http://qa-auto01.on24.com:8080/jenkins/job/qa-vsa-desktop-sl/SELENIUM_DRIVER=Windows_2012_R2internet_explorer11,TEST_SET=daily1/5611/cucumber-html-reports","hex":"#8BC34A","time":"1h 11min","value":100,"config":"Win 8.1 IE 11"},{"fail":"0 (0.0%)","total":137,"pass":"137 (100.0%)","module":"daily1","name":"Fail","link":"http://qa-auto01.on24.com:8080/jenkins/job/qa-vsa-desktop-sl/SELENIUM_DRIVER=Windows_2012_R2internet_explorer11,TEST_SET=daily1/5611/cucumber-html-reports","hex":"#b22200","time":"1h 11min","value":0,"config":"Win 8.1 IE 11"},{"fail":"2 (1.2%)","total":170,"pass":"168 (98.8%)","module":"daily2","name":"Pass","link":"http://qa-auto01.on24.com:8080/jenkins/job/qa-vsa-desktop-sl/SELENIUM_DRIVER=Windows_2012_R2internet_explorer11,TEST_SET=daily2/5612/cucumber-html-reports","hex":"#8BC34A","time":"1h 1min","value":98.8,"config":"Win 8.1 IE 11"},{"fail":"2 (1.2%)","total":170,"pass":"168 (98.8%)","module":"daily2","name":"Fail","link":"http://qa-auto01.on24.com:8080/jenkins/job/qa-vsa-desktop-sl/SELENIUM_DRIVER=Windows_2012_R2internet_explorer11,TEST_SET=daily2/5612/cucumber-html-reports","hex":"#b22200","time":"1h 1min","value":1.2,"config":"Win 8.1 IE 11"}],"title":"Weekly Health - VE Desktop (Win 8.1 IE 11)"},"vsadesktopWindows_2008internet_explorer11WeeklyHealth":{"data":[{"fail":"6 (20.0%)","total":30,"pass":"24 (80.0%)","module":"rerun","name":"Pass","link":"http://qa-auto01.on24.com:8080/jenkins/job/qa-vsa-desktop-sl/SELENIUM_DRIVER=Windows_2008internet_explorer11,TEST_SET=rerun/5617/cucumber-html-reports","hex":"#8BC34A","time":"0h 30min","value":80,"config":"Win 7 IE 11"},{"fail":"6 (20.0%)","total":30,"pass":"24 (80.0%)","module":"rerun","name":"Fail","link":"http://qa-auto01.on24.com:8080/jenkins/job/qa-vsa-desktop-sl/SELENIUM_DRIVER=Windows_2008internet_explorer11,TEST_SET=rerun/5617/cucumber-html-reports","hex":"#b22200","time":"0h 30min","value":20,"config":"Win 7 IE 11"},{"fail":"17 (100.0%)","total":17,"pass":"0 (0.0%)","module":"green","name":"Pass","link":"http://qa-auto01.on24.com:8080/jenkins/job/qa-vsa-desktop-sl/SELENIUM_DRIVER=Windows_2008internet_explorer11,TEST_SET=green/0/cucumber-html-reports","hex":"#8BC34A","time":"0h 43min","value":0,"config":"Win 7 IE 11"},{"fail":"17 (100.0%)","total":17,"pass":"0 (0.0%)","module":"green","name":"Fail","link":"http://qa-auto01.on24.com:8080/jenkins/job/qa-vsa-desktop-sl/SELENIUM_DRIVER=Windows_2008internet_explorer11,TEST_SET=green/0/cucumber-html-reports","hex":"#b22200","time":"0h 43min","value":100,"config":"Win 7 IE 11"},{"fail":"18 (13.1%)","total":137,"pass":"119 (86.9%)","module":"daily1","name":"Pass","link":"http://qa-auto01.on24.com:8080/jenkins/job/qa-vsa-desktop-sl/SELENIUM_DRIVER=Windows_2008internet_explorer11,TEST_SET=daily1/5615/cucumber-html-reports","hex":"#8BC34A","time":"1h 44min","value":86.9,"config":"Win 7 IE 11"},{"fail":"18 (13.1%)","total":137,"pass":"119 (86.9%)","module":"daily1","name":"Fail","link":"http://qa-auto01.on24.com:8080/jenkins/job/qa-vsa-desktop-sl/SELENIUM_DRIVER=Windows_2008internet_explorer11,TEST_SET=daily1/5615/cucumber-html-reports","hex":"#b22200","time":"1h 44min","value":13.1,"config":"Win 7 IE 11"},{"fail":"8 (4.7%)","total":170,"pass":"162 (95.3%)","module":"daily2","name":"Pass","link":"http://qa-auto01.on24.com:8080/jenkins/job/qa-vsa-desktop-sl/SELENIUM_DRIVER=Windows_2008internet_explorer11,TEST_SET=daily2/5616/cucumber-html-reports","hex":"#8BC34A","time":"1h 22min","value":95.3,"config":"Win 7 IE 11"},{"fail":"8 (4.7%)","total":170,"pass":"162 (95.3%)","module":"daily2","name":"Fail","link":"http://qa-auto01.on24.com:8080/jenkins/job/qa-vsa-desktop-sl/SELENIUM_DRIVER=Windows_2008internet_explorer11,TEST_SET=daily2/5616/cucumber-html-reports","hex":"#b22200","time":"1h 22min","value":4.7,"config":"Win 7 IE 11"}],"title":"Weekly Health - VE Desktop (Win 7 IE 11)"},"vsadesktopWindows_2008firefoxlatestWeeklyHealth":{"data":[{"fail":"0 (0.0%)","total":1,"pass":"1 (100.0%)","module":"rerun","name":"Pass","link":"http://qa-auto01.on24.com:8080/jenkins/job/qa-vsa-desktop-sl/SELENIUM_DRIVER=Windows_2008firefoxlatest,TEST_SET=rerun/5595/cucumber-html-reports","hex":"#8BC34A","time":"0h 1min","value":100,"config":"Win 7 FF (l)"},{"fail":"0 (0.0%)","total":1,"pass":"1 (100.0%)","module":"rerun","name":"Fail","link":"http://qa-auto01.on24.com:8080/jenkins/job/qa-vsa-desktop-sl/SELENIUM_DRIVER=Windows_2008firefoxlatest,TEST_SET=rerun/5595/cucumber-html-reports","hex":"#b22200","time":"0h 1min","value":0,"config":"Win 7 FF (l)"},{"fail":"0 (0.0%)","total":16,"pass":"16 (100.0%)","module":"green","name":"Pass","link":"http://qa-auto01.on24.com:8080/jenkins/job/qa-vsa-desktop-sl/SELENIUM_DRIVER=Windows_2008firefoxlatest,TEST_SET=green/5592/cucumber-html-reports","hex":"#8BC34A","time":"0h 9min","value":100,"config":"Win 7 FF (l)"},{"fail":"0 (0.0%)","total":16,"pass":"16 (100.0%)","module":"green","name":"Fail","link":"http://qa-auto01.on24.com:8080/jenkins/job/qa-vsa-desktop-sl/SELENIUM_DRIVER=Windows_2008firefoxlatest,TEST_SET=green/5592/cucumber-html-reports","hex":"#b22200","time":"0h 9min","value":0,"config":"Win 7 FF (l)"},{"fail":"1 (0.7%)","total":137,"pass":"136 (99.3%)","module":"daily1","name":"Pass","link":"http://qa-auto01.on24.com:8080/jenkins/job/qa-vsa-desktop-sl/SELENIUM_DRIVER=Windows_2008firefoxlatest,TEST_SET=daily1/5593/cucumber-html-reports","hex":"#8BC34A","time":"1h 8min","value":99.3,"config":"Win 7 FF (l)"},{"fail":"1 (0.7%)","total":137,"pass":"136 (99.3%)","module":"daily1","name":"Fail","link":"http://qa-auto01.on24.com:8080/jenkins/job/qa-vsa-desktop-sl/SELENIUM_DRIVER=Windows_2008firefoxlatest,TEST_SET=daily1/5593/cucumber-html-reports","hex":"#b22200","time":"1h 8min","value":0.7,"config":"Win 7 FF (l)"},{"fail":"0 (0.0%)","total":170,"pass":"170 (100.0%)","module":"daily2","name":"Pass","link":"http://qa-auto01.on24.com:8080/jenkins/job/qa-vsa-desktop-sl/SELENIUM_DRIVER=Windows_2008firefoxlatest,TEST_SET=daily2/5594/cucumber-html-reports","hex":"#8BC34A","time":"0h 58min","value":100,"config":"Win 7 FF (l)"},{"fail":"0 (0.0%)","total":170,"pass":"170 (100.0%)","module":"daily2","name":"Fail","link":"http://qa-auto01.on24.com:8080/jenkins/job/qa-vsa-desktop-sl/SELENIUM_DRIVER=Windows_2008firefoxlatest,TEST_SET=daily2/5594/cucumber-html-reports","hex":"#b22200","time":"0h 58min","value":0,"config":"Win 7 FF (l)"}],"title":"Weekly Health - VE Desktop (Win 7 FF (l))"},"vsadesktopMac_10_12firefoxlatestWeeklyHealth":{"data":[{"fail":"1 (25.0%)","total":4,"pass":"3 (75.0%)","module":"rerun","name":"Pass","link":"http://qa-auto01.on24.com:8080/jenkins/job/qa-vsa-desktop-sl/SELENIUM_DRIVER=Mac_10_12firefoxlatest,TEST_SET=rerun/5603/cucumber-html-reports","hex":"#8BC34A","time":"0h 35min","value":75,"config":"Mac 10.12 FF (l)"},{"fail":"1 (25.0%)","total":4,"pass":"3 (75.0%)","module":"rerun","name":"Fail","link":"http://qa-auto01.on24.com:8080/jenkins/job/qa-vsa-desktop-sl/SELENIUM_DRIVER=Mac_10_12firefoxlatest,TEST_SET=rerun/5603/cucumber-html-reports","hex":"#b22200","time":"0h 35min","value":25,"config":"Mac 10.12 FF (l)"},{"fail":"0 (0.0%)","total":16,"pass":"16 (100.0%)","module":"green","name":"Pass","link":"http://qa-auto01.on24.com:8080/jenkins/job/qa-vsa-desktop-sl/SELENIUM_DRIVER=Mac_10_12firefoxlatest,TEST_SET=green/5600/cucumber-html-reports","hex":"#8BC34A","time":"0h 6min","value":100,"config":"Mac 10.12 FF (l)"},{"fail":"0 (0.0%)","total":16,"pass":"16 (100.0%)","module":"green","name":"Fail","link":"http://qa-auto01.on24.com:8080/jenkins/job/qa-vsa-desktop-sl/SELENIUM_DRIVER=Mac_10_12firefoxlatest,TEST_SET=green/5600/cucumber-html-reports","hex":"#b22200","time":"0h 6min","value":0,"config":"Mac 10.12 FF (l)"},{"fail":"2 (1.5%)","total":137,"pass":"135 (98.5%)","module":"daily1","name":"Pass","link":"http://qa-auto01.on24.com:8080/jenkins/job/qa-vsa-desktop-sl/SELENIUM_DRIVER=Mac_10_12firefoxlatest,TEST_SET=daily1/5601/cucumber-html-reports","hex":"#8BC34A","time":"1h 28min","value":98.5,"config":"Mac 10.12 FF (l)"},{"fail":"2 (1.5%)","total":137,"pass":"135 (98.5%)","module":"daily1","name":"Fail","link":"http://qa-auto01.on24.com:8080/jenkins/job/qa-vsa-desktop-sl/SELENIUM_DRIVER=Mac_10_12firefoxlatest,TEST_SET=daily1/5601/cucumber-html-reports","hex":"#b22200","time":"1h 28min","value":1.5,"config":"Mac 10.12 FF (l)"},{"fail":"2 (1.2%)","total":170,"pass":"168 (98.8%)","module":"daily2","name":"Pass","link":"http://qa-auto01.on24.com:8080/jenkins/job/qa-vsa-desktop-sl/SELENIUM_DRIVER=Mac_10_12firefoxlatest,TEST_SET=daily2/5602/cucumber-html-reports","hex":"#8BC34A","time":"0h 55min","value":98.8,"config":"Mac 10.12 FF (l)"},{"fail":"2 (1.2%)","total":170,"pass":"168 (98.8%)","module":"daily2","name":"Fail","link":"http://qa-auto01.on24.com:8080/jenkins/job/qa-vsa-desktop-sl/SELENIUM_DRIVER=Mac_10_12firefoxlatest,TEST_SET=daily2/5602/cucumber-html-reports","hex":"#b22200","time":"0h 55min","value":1.2,"config":"Mac 10.12 FF (l)"}],"title":"Weekly Health - VE Desktop (Mac 10.12 FF (l))"},"vsadesktopWindows_2008chromebetaWeeklyHealth":{"data":[{"fail":"0 (0.0%)","total":1,"pass":"1 (100.0%)","module":"rerun","name":"Pass","link":"http://qa-auto01.on24.com:8080/jenkins/job/qa-vsa-desktop-sl/SELENIUM_DRIVER=Windows_2008chromebeta,TEST_SET=rerun/5624/cucumber-html-reports","hex":"#8BC34A","time":"0h 2min","value":100,"config":"Win 7 chrome (b)"},{"fail":"0 (0.0%)","total":1,"pass":"1 (100.0%)","module":"rerun","name":"Fail","link":"http://qa-auto01.on24.com:8080/jenkins/job/qa-vsa-desktop-sl/SELENIUM_DRIVER=Windows_2008chromebeta,TEST_SET=rerun/5624/cucumber-html-reports","hex":"#b22200","time":"0h 2min","value":0,"config":"Win 7 chrome (b)"},{"fail":"0 (0.0%)","total":16,"pass":"16 (100.0%)","module":"green","name":"Pass","link":"http://qa-auto01.on24.com:8080/jenkins/job/qa-vsa-desktop-sl/SELENIUM_DRIVER=Windows_2008chromebeta,TEST_SET=green/5621/cucumber-html-reports","hex":"#8BC34A","time":"0h 10min","value":100,"config":"Win 7 chrome (b)"},{"fail":"0 (0.0%)","total":16,"pass":"16 (100.0%)","module":"green","name":"Fail","link":"http://qa-auto01.on24.com:8080/jenkins/job/qa-vsa-desktop-sl/SELENIUM_DRIVER=Windows_2008chromebeta,TEST_SET=green/5621/cucumber-html-reports","hex":"#b22200","time":"0h 10min","value":0,"config":"Win 7 chrome (b)"},{"fail":"1 (0.7%)","total":137,"pass":"136 (99.3%)","module":"daily1","name":"Pass","link":"http://qa-auto01.on24.com:8080/jenkins/job/qa-vsa-desktop-sl/SELENIUM_DRIVER=Windows_2008chromebeta,TEST_SET=daily1/5622/cucumber-html-reports","hex":"#8BC34A","time":"1h 38min","value":99.3,"config":"Win 7 chrome (b)"},{"fail":"1 (0.7%)","total":137,"pass":"136 (99.3%)","module":"daily1","name":"Fail","link":"http://qa-auto01.on24.com:8080/jenkins/job/qa-vsa-desktop-sl/SELENIUM_DRIVER=Windows_2008chromebeta,TEST_SET=daily1/5622/cucumber-html-reports","hex":"#b22200","time":"1h 38min","value":0.7,"config":"Win 7 chrome (b)"},{"fail":"0 (0.0%)","total":170,"pass":"170 (100.0%)","module":"daily2","name":"Pass","link":"http://qa-auto01.on24.com:8080/jenkins/job/qa-vsa-desktop-sl/SELENIUM_DRIVER=Windows_2008chromebeta,TEST_SET=daily2/5623/cucumber-html-reports","hex":"#8BC34A","time":"1h 11min","value":100,"config":"Win 7 chrome (b)"},{"fail":"0 (0.0%)","total":170,"pass":"170 (100.0%)","module":"daily2","name":"Fail","link":"http://qa-auto01.on24.com:8080/jenkins/job/qa-vsa-desktop-sl/SELENIUM_DRIVER=Windows_2008chromebeta,TEST_SET=daily2/5623/cucumber-html-reports","hex":"#b22200","time":"1h 11min","value":0,"config":"Win 7 chrome (b)"}],"title":"Weekly Health - VE Desktop (Win 7 chrome (b))"}},"barData":[{"innerData":"vsadesktopWindows_2008internet_explorer11WeeklyHealth","fail":"6 (1.9%)","total":311,"pass":"305 (98.1%)","module":"Win 7 IE 11","name":"Pass","report":"weekly","hex":"#8BC34A","value":98.1,"config":"Win 7 IE 11"},{"innerData":"vsadesktopWindows_10microsoftedge14WeeklyHealth","fail":"5 (1.4%)","total":365,"pass":"360 (98.6%)","module":"Win 10 ms edge 14","name":"Pass","report":"weekly","hex":"#8BC34A","value":98.6,"config":"Win 10 ms edge 14"},{"innerData":"vsadesktopWindows_2012_R2internet_explorer11WeeklyHealth","fail":"2 (0.7%)","total":307,"pass":"305 (99.3%)","module":"Win 8.1 IE 11","name":"Pass","report":"weekly","hex":"#8BC34A","value":99.3,"config":"Win 8.1 IE 11"},{"innerData":"vsadesktopMac_10_12firefoxlatestWeeklyHealth","fail":"1 (0.3%)","total":323,"pass":"322 (99.7%)","module":"Mac 10.12 FF (l)","name":"Pass","report":"weekly","hex":"#8BC34A","value":99.7,"config":"Mac 10.12 FF (l)"},{"innerData":"vsadesktopWindows_2008firefoxlatestWeeklyHealth","fail":"1 (0.3%)","total":324,"pass":"323 (99.7%)","module":"Win 7 FF (l)","name":"Pass","report":"weekly","hex":"#8BC34A","value":99.7,"config":"Win 7 FF (l)"},{"innerData":"vsadesktopWindows_2012_R2chromebetaWeeklyHealth","fail":"1 (0.3%)","total":324,"pass":"323 (99.7%)","module":"Win 8.1 chrome (b)","name":"Pass","report":"weekly","hex":"#8BC34A","value":99.7,"config":"Win 8.1 chrome (b)"},{"innerData":"vsadesktopWindows_2008chromebetaWeeklyHealth","fail":"1 (0.3%)","total":324,"pass":"323 (99.7%)","module":"Win 7 chrome (b)","name":"Pass","report":"weekly","hex":"#8BC34A","value":99.7,"config":"Win 7 chrome (b)"},{"innerData":"vsadesktopWindows_2008internet_explorer11WeeklyHealth","fail":"6 (1.9%)","total":311,"pass":"305 (98.1%)","module":"Win 7 IE 11","name":"Fail","report":"weekly","hex":"#b22200","value":1.9,"config":"Win 7 IE 11"},{"innerData":"vsadesktopWindows_10microsoftedge14WeeklyHealth","fail":"5 (1.4%)","total":365,"pass":"360 (98.6%)","module":"Win 10 ms edge 14","name":"Fail","report":"weekly","hex":"#b22200","value":1.4,"config":"Win 10 ms edge 14"},{"innerData":"vsadesktopWindows_2012_R2internet_explorer11WeeklyHealth","fail":"2 (0.7%)","total":307,"pass":"305 (99.3%)","module":"Win 8.1 IE 11","name":"Fail","report":"weekly","hex":"#b22200","value":0.7,"config":"Win 8.1 IE 11"},{"innerData":"vsadesktopMac_10_12firefoxlatestWeeklyHealth","fail":"1 (0.3%)","total":323,"pass":"322 (99.7%)","module":"Mac 10.12 FF (l)","name":"Fail","report":"weekly","hex":"#b22200","value":0.3,"config":"Mac 10.12 FF (l)"},{"innerData":"vsadesktopWindows_2008firefoxlatestWeeklyHealth","fail":"1 (0.3%)","total":324,"pass":"323 (99.7%)","module":"Win 7 FF (l)","name":"Fail","report":"weekly","hex":"#b22200","value":0.3,"config":"Win 7 FF (l)"},{"innerData":"vsadesktopWindows_2012_R2chromebetaWeeklyHealth","fail":"1 (0.3%)","total":324,"pass":"323 (99.7%)","module":"Win 8.1 chrome (b)","name":"Fail","report":"weekly","hex":"#b22200","value":0.3,"config":"Win 8.1 chrome (b)"},{"innerData":"vsadesktopWindows_2008chromebetaWeeklyHealth","fail":"1 (0.3%)","total":324,"pass":"323 (99.7%)","module":"Win 7 chrome (b)","name":"Fail","report":"weekly","hex":"#b22200","value":0.3,"config":"Win 7 chrome (b)"}],"countPassedFailed":2278,"graphData":[{"percentage":0,"name":"passed","value":2261},{"percentage":0,"name":"failed","value":17}],"title":"Weekly Health","barDataTitle":"Weekly Health - VE Desktop (Configuration Wise)","execution_time":"21h 25min"},"green_report":{"date":"05 Mar 19 10:37 PM","barData":[{"fail":"0 (0.0%)","total":3,"pass":"3 (100.0%)","module":"desktopRegistration","name":"Pass","link":"http://qa-auto01.on24.com:8080/jenkins/job/qa-vsa-desktop-sl/SELENIUM_DRIVER=Windows_2012_R2chromebeta,TEST_SET=green/5629/cucumber-html-reports","hex":"#8BC34A","time":"0h 9min","value":100,"config":"Win 8.1 chrome (b)"},{"fail":"0 (0.0%)","total":1,"pass":"1 (100.0%)","module":"login","name":"Pass","link":"http://qa-auto01.on24.com:8080/jenkins/job/qa-vsa-desktop-sl/SELENIUM_DRIVER=Windows_2012_R2chromebeta,TEST_SET=green/5629/cucumber-html-reports","hex":"#8BC34A","time":"0h 9min","value":100,"config":"Win 8.1 chrome (b)"},{"fail":"0 (0.0%)","total":1,"pass":"1 (100.0%)","module":"registration","name":"Pass","link":"http://qa-auto01.on24.com:8080/jenkins/job/qa-vsa-desktop-sl/SELENIUM_DRIVER=Windows_2012_R2chromebeta,TEST_SET=green/5629/cucumber-html-reports","hex":"#8BC34A","time":"0h 9min","value":100,"config":"Win 8.1 chrome (b)"},{"fail":"0 (0.0%)","total":4,"pass":"4 (100.0%)","module":"desktopLogin","name":"Pass","link":"http://qa-auto01.on24.com:8080/jenkins/job/qa-vsa-desktop-sl/SELENIUM_DRIVER=Windows_2012_R2chromebeta,TEST_SET=green/5629/cucumber-html-reports","hex":"#8BC34A","time":"0h 9min","value":100,"config":"Win 8.1 chrome (b)"},{"fail":"0 (0.0%)","total":6,"pass":"6 (100.0%)","module":"subNavigation","name":"Pass","link":"http://qa-auto01.on24.com:8080/jenkins/job/qa-vsa-desktop-sl/SELENIUM_DRIVER=Windows_2012_R2chromebeta,TEST_SET=green/5629/cucumber-html-reports","hex":"#8BC34A","time":"0h 9min","value":100,"config":"Win 8.1 chrome (b)"},{"fail":"0 (0.0%)","total":1,"pass":"1 (100.0%)","module":"mainNavigation","name":"Pass","link":"http://qa-auto01.on24.com:8080/jenkins/job/qa-vsa-desktop-sl/SELENIUM_DRIVER=Windows_2012_R2chromebeta,TEST_SET=green/5629/cucumber-html-reports","hex":"#8BC34A","time":"0h 9min","value":100,"config":"Win 8.1 chrome (b)"}],"countPassedFailed":16,"browserName":"chrome (B)","cucumberReportUrl":"http://qa-auto01.on24.com:8080/jenkins/job/qa-vsa-desktop-sl/SELENIUM_DRIVER=Windows_2012_R2chromebeta,TEST_SET=green/5629/cucumber-html-reports","graphData":[{"percentage":0,"name":"failed","value":0},{"percentage":0,"name":"passed","value":16}],"title":"Last Green Run","barDataTitle":"Last Green (Smoke )Run - VE-Desktop Module Wise","platform":"Win 8.1","execution_time":"0h 9min"},"current_report":{"date":"04 Mar 19 10:56 PM","barData":[{"fail":"0 (0.0%)","total":1,"pass":"1 (100.0%)","module":"rerun","name":"Pass","link":"http://qa-auto01.on24.com:8080/jenkins/job/qa-vsa-desktop-sl/SELENIUM_DRIVER=Windows_2008chromebeta,TEST_SET=rerun/5624/cucumber-html-reports","hex":"#8BC34A","time":"0h 2min","value":100,"config":"Win 7 chrome (b)"},{"fail":"0 (0.0%)","total":1,"pass":"1 (100.0%)","module":"rerun","name":"Fail","link":"http://qa-auto01.on24.com:8080/jenkins/job/qa-vsa-desktop-sl/SELENIUM_DRIVER=Windows_2008chromebeta,TEST_SET=rerun/5624/cucumber-html-reports","hex":"#b22200","time":"0h 2min","value":0,"config":"Win 7 chrome (b)"},{"fail":"0 (0.0%)","total":16,"pass":"16 (100.0%)","module":"green","name":"Pass","link":"http://qa-auto01.on24.com:8080/jenkins/job/qa-vsa-desktop-sl/SELENIUM_DRIVER=Windows_2008chromebeta,TEST_SET=green/5621/cucumber-html-reports","hex":"#8BC34A","time":"0h 10min","value":100,"config":"Win 7 chrome (b)"},{"fail":"0 (0.0%)","total":16,"pass":"16 (100.0%)","module":"green","name":"Fail","link":"http://qa-auto01.on24.com:8080/jenkins/job/qa-vsa-desktop-sl/SELENIUM_DRIVER=Windows_2008chromebeta,TEST_SET=green/5621/cucumber-html-reports","hex":"#b22200","time":"0h 10min","value":0,"config":"Win 7 chrome (b)"},{"fail":"1 (0.7%)","total":137,"pass":"136 (99.3%)","module":"daily1","name":"Pass","link":"http://qa-auto01.on24.com:8080/jenkins/job/qa-vsa-desktop-sl/SELENIUM_DRIVER=Windows_2008chromebeta,TEST_SET=daily1/5622/cucumber-html-reports","hex":"#8BC34A","time":"1h 38min","value":99.3,"config":"Win 7 chrome (b)"},{"fail":"1 (0.7%)","total":137,"pass":"136 (99.3%)","module":"daily1","name":"Fail","link":"http://qa-auto01.on24.com:8080/jenkins/job/qa-vsa-desktop-sl/SELENIUM_DRIVER=Windows_2008chromebeta,TEST_SET=daily1/5622/cucumber-html-reports","hex":"#b22200","time":"1h 38min","value":0.7,"config":"Win 7 chrome (b)"},{"fail":"0 (0.0%)","total":170,"pass":"170 (100.0%)","module":"daily2","name":"Pass","link":"http://qa-auto01.on24.com:8080/jenkins/job/qa-vsa-desktop-sl/SELENIUM_DRIVER=Windows_2008chromebeta,TEST_SET=daily2/5623/cucumber-html-reports","hex":"#8BC34A","time":"1h 11min","value":100,"config":"Win 7 chrome (b)"},{"fail":"0 (0.0%)","total":170,"pass":"170 (100.0%)","module":"daily2","name":"Fail","link":"http://qa-auto01.on24.com:8080/jenkins/job/qa-vsa-desktop-sl/SELENIUM_DRIVER=Windows_2008chromebeta,TEST_SET=daily2/5623/cucumber-html-reports","hex":"#b22200","time":"1h 11min","value":0,"config":"Win 7 chrome (b)"}],"countPassedFailed":324,"browserName":"chrome (B)","graphData":[{"percentage":0,"name":"passed","value":323},{"percentage":0,"name":"failed","value":1}],"title":"Last 24 Hours","barDataTitle":"Last 24 Hours Run - VE Desktop (Win 7 chrome (B))","platform":"Win 7","execution_time":"3h 1min"},"project_title":"VSHOW > VSA-DESKTOP"}}